utmcon/__init__.py
utmcon/main.py
utmcon-0.31.dist-info/LICENCE.txt
utmcon-0.31.dist-info/METADATA
utmcon-0.31.dist-info/WHEEL
utmcon-0.31.dist-info/top_level.txt
utmcon-0.31.dist-info/RECORD
