Metadata-Version: 1.0
Name: utmcon
Version: 0.31
Summary: Convert UTM to lat long.
Home-page: http://github.com/rbutus/utmcon
Author: Ryan Trigg
Author-email: rbutustree@gmail.com
License: MIT
Platform: UNKNOWN
